access_logs_local-0.1.0.dist-info/licenses/LICENSE
access_logs_local_driver/__init__.py
access_logs_local_driver/geolookup.py
access_logs_local_driver/logdata.py
access_logs_local_driver/process_download_logs.py
access_logs_local-0.1.0.dist-info/METADATA
access_logs_local-0.1.0.dist-info/WHEEL
access_logs_local-0.1.0.dist-info/top_level.txt
access_logs_local-0.1.0.dist-info/RECORD
