Metadata-Version: 2.4
Name: access_logs_local
Version: 0.1.0
Summary: Functions required by the access-logs-local-driver
Author-email: Cristian Garcia <cristian.garcia@ubiquitypress.com>
Classifier: Programming Language :: Python :: 3
Classifier: License :: OSI Approved :: MIT License
Classifier: Operating System :: OS Independent
Requires-Python: >=3.10
License-File: LICENSE
Dynamic: license-file
